droidrun/__init__.py
droidrun/__main__.py
droidrun/config_example.yaml
droidrun/portal.py
droidrun/agent/__init__.py
droidrun/agent/usage.py
droidrun/agent/codeact/__init__.py
droidrun/agent/codeact/codeact_agent.py
droidrun/agent/codeact/events.py
droidrun/agent/common/__init__.py
droidrun/agent/common/constants.py
droidrun/agent/common/events.py
droidrun/agent/droid/__init__.py
droidrun/agent/droid/droid_agent.py
droidrun/agent/droid/events.py
droidrun/agent/droid/state.py
droidrun/agent/executor/__init__.py
droidrun/agent/executor/events.py
droidrun/agent/executor/executor_agent.py
droidrun/agent/executor/prompts.py
droidrun/agent/external/__init__.py
droidrun/agent/external/autoglm.py
droidrun/agent/external/mai_ui.py
droidrun/agent/manager/__init__.py
droidrun/agent/manager/events.py
droidrun/agent/manager/manager_agent.py
droidrun/agent/manager/prompts.py
droidrun/agent/manager/stateless_manager_agent.py
droidrun/agent/oneflows/__init__.py
droidrun/agent/oneflows/app_starter_workflow.py
droidrun/agent/oneflows/structured_output_agent.py
droidrun/agent/oneflows/text_manipulator.py
droidrun/agent/scripter/__init__.py
droidrun/agent/scripter/events.py
droidrun/agent/scripter/scripter_agent.py
droidrun/agent/trajectory/__init__.py
droidrun/agent/trajectory/writer.py
droidrun/agent/utils/__init__.py
droidrun/agent/utils/actions.py
droidrun/agent/utils/chat_utils.py
droidrun/agent/utils/code_checker.py
droidrun/agent/utils/executer.py
droidrun/agent/utils/inference.py
droidrun/agent/utils/llm_loader.py
droidrun/agent/utils/llm_picker.py
droidrun/agent/utils/prompt_resolver.py
droidrun/agent/utils/signatures.py
droidrun/agent/utils/tools.py
droidrun/agent/utils/tracing_setup.py
droidrun/agent/utils/trajectory.py
droidrun/app_cards/__init__.py
droidrun/app_cards/app_card_provider.py
droidrun/app_cards/providers/__init__.py
droidrun/app_cards/providers/composite_provider.py
droidrun/app_cards/providers/local_provider.py
droidrun/app_cards/providers/server_provider.py
droidrun-0.4.23.dist-info/METADATA
droidrun-0.4.23.dist-info/WHEEL
droidrun-0.4.23.dist-info/entry_points.txt
droidrun-0.4.23.dist-info/licenses/LICENSE
droidrun-0.4.23.dist-info/RECORD
