Metadata-Version: 2.4
Name: droidrun
Version: 0.4.23
Summary: A framework for controlling Android devices through LLM agents
Project-URL: Homepage, https://github.com/droidrun/droidrun
Project-URL: Bug Tracker, https://github.com/droidrun/droidrun/issues
Project-URL: Documentation, https://docs.droidrun.ai/
Author-email: Niels Schmidt <niels.schmidt@droidrun.ai>
License: MIT
License-File: LICENSE
Classifier: Development Status :: 4 - Beta
Classifier: Intended Audience :: Developers
Classifier: Intended Audience :: Information Technology
Classifier: Intended Audience :: Science/Research
Classifier: License :: OSI Approved :: MIT License
Classifier: Programming Language :: Python :: 3.11
Classifier: Programming Language :: Python :: 3.12
Classifier: Programming Language :: Python :: 3.13
Classifier: Topic :: Communications :: Chat
Classifier: Topic :: Scientific/Engineering :: Artificial Intelligence
Classifier: Topic :: Software Development :: Libraries :: Application Frameworks
Classifier: Topic :: Software Development :: Libraries :: Python Modules
Classifier: Topic :: Software Development :: Quality Assurance
Classifier: Topic :: Software Development :: Testing
Classifier: Topic :: Software Development :: Testing :: Acceptance
Classifier: Topic :: System :: Emulators
Classifier: Topic :: Utilities
Requires-Python: >=3.11
Requires-Dist: aiofiles>=25.1.0
Requires-Dist: arize-phoenix>=12.3.0
Requires-Dist: async-adbutils
Requires-Dist: httpx>=0.27.0
Requires-Dist: llama-index-callbacks-arize-phoenix>=0.6.1
Requires-Dist: llama-index-workflows==2.8.3
Requires-Dist: llama-index==0.14.4
Requires-Dist: posthog>=6.7.6
Requires-Dist: pydantic>=2.11.10
Requires-Dist: rich>=14.1.0
Requires-Dist: textual>=6.11.0
Provides-Extra: anthropic
Requires-Dist: anthropic>=0.67.0; extra == 'anthropic'
Requires-Dist: llama-index-llms-anthropic<0.9.0,>=0.8.6; extra == 'anthropic'
Provides-Extra: deepseek
Requires-Dist: llama-index-llms-deepseek>=0.2.1; extra == 'deepseek'
Provides-Extra: dev
Requires-Dist: bandit>=1.8.6; extra == 'dev'
Requires-Dist: black==25.9.0; extra == 'dev'
Requires-Dist: langfuse==3.9.0; extra == 'dev'
Requires-Dist: llama-index-instrumentation; extra == 'dev'
Requires-Dist: llama-index-llms-google-genai>=0.3.1; extra == 'dev'
Requires-Dist: mypy>=1.0.0; extra == 'dev'
Requires-Dist: openinference-instrumentation-llama-index>=3.0.0; extra == 'dev'
Requires-Dist: ruff>=0.13.0; extra == 'dev'
Requires-Dist: safety>=3.2.11; extra == 'dev'
Provides-Extra: google
Requires-Dist: llama-index-llms-google-genai>=0.3.1; extra == 'google'
Provides-Extra: langfuse
Requires-Dist: langfuse==3.9.0; extra == 'langfuse'
Requires-Dist: llama-index-instrumentation; extra == 'langfuse'
Requires-Dist: openinference-instrumentation-llama-index>=3.0.0; extra == 'langfuse'
Provides-Extra: mobilerun
Requires-Dist: mobilerun-sdk; extra == 'mobilerun'
Provides-Extra: ollama
Requires-Dist: llama-index-llms-ollama>=0.7.2; extra == 'ollama'
Provides-Extra: openai
Requires-Dist: llama-index-llms-openai-like>=0.5.1; extra == 'openai'
Requires-Dist: llama-index-llms-openai>=0.5.6; extra == 'openai'
Requires-Dist: openai>=1.99.1; extra == 'openai'
Provides-Extra: openrouter
Requires-Dist: llama-index-llms-openrouter>=0.4.2; extra == 'openrouter'
